vl53l0x_python.so
VL53L0X.py
VL53L0X-1.0.4.dist-info/metadata.json
VL53L0X-1.0.4.dist-info/WHEEL
VL53L0X-1.0.4.dist-info/METADATA
VL53L0X-1.0.4.dist-info/DESCRIPTION.rst
VL53L0X-1.0.4.dist-info/top_level.txt
VL53L0X-1.0.4.dist-info/RECORD
