Metadata-Version: 2.0
Name: VL53L0X
Version: 1.0.4
Summary: VL53L0X sensor for raspberry PI/JetsonTX2
Home-page: https://github.com/pimoroni/VL53L0X_rasp_python
Author: UNKNOWN
Author-email: UNKNOWN
License: UNKNOWN
Platform: UNKNOWN
Requires: smbus
